pushplush/__init__.py
pushplush/push.py
pushplush-0.0.2.dist-info/LICENSE
pushplush-0.0.2.dist-info/METADATA
pushplush-0.0.2.dist-info/WHEEL
pushplush-0.0.2.dist-info/top_level.txt
pushplush-0.0.2.dist-info/RECORD
