Metadata-Version: 2.1
Name: pushplush
Version: 0.0.2
Summary: A small pushplush package
Home-page: http://aotuman.xyz
Author: 凹凸曼大人r
Author-email: a15512431228@163.com
License: UNKNOWN
Platform: UNKNOWN
Classifier: Programming Language :: Python :: 3
Classifier: License :: OSI Approved :: MIT License
Classifier: Operating System :: OS Independent
Requires-Python: >=3.6
License-File: LICENSE
